jureap/__init__.py
jureap/metadata.py
jureap/check/__init__.py
jureap/cli/__init__.py
jureap/detail/__init__.py
jureap/log/__init__.py
jureap/report/__init__.py
jureap-2.1.6.data/data/share/jureap/tex/jedi/.gitignore
jureap-2.1.6.data/data/share/jureap/tex/jedi/document.mk
jureap-2.1.6.data/data/share/jureap/tex/jedi/jureap.cls
jureap-2.1.6.data/data/share/jureap/tex/jedi/makefile
jureap-2.1.6.data/data/share/jureap/tex/jedi/report.tex
jureap-2.1.6.dist-info/METADATA
jureap-2.1.6.dist-info/WHEEL
jureap-2.1.6.dist-info/entry_points.txt
jureap-2.1.6.dist-info/RECORD
