Metadata-Version: 2.3
Name: jureap
Version: 2.1.6
Summary: A helper script for the jureap project
Project-URL: Documentation, https://gitlab.jsc.fz-juelich.de/exacb/jureap
Project-URL: Issues, https://gitlab.jsc.fz-juelich.de/exacb/jureap
Project-URL: Source, https://gitlab.jsc.fz-juelich.de/exacb/jureap
Author-email: Jayesh Badwaik <j.badwaik@fz-juelich.de>
License-Expression: Apache-2.0
Requires-Dist: semver
